[{"data":"2020-06-01 00:00:00","ios":137295,"android":172357,"ios_android":309652,"ios_total":137295,"android_total":172357,"ios_android_total":309652},{"data":"2020-06-02 00:00:00","ios":234694,"android":425222,"ios_android":659916,"ios_total":371989,"android_total":597579,"ios_android_total":969568},{"data":"2020-06-03 00:00:00","ios":187097,"android":226894,"ios_android":413991,"ios_total":559086,"android_total":824473,"ios_android_total":1383559},{"data":"2020-06-04 00:00:00","ios":76492,"android":91275,"ios_android":167767,"ios_total":635578,"android_total":915748,"ios_android_total":1551326},{"data":"2020-06-05 00:00:00","ios":50510,"android":48847,"ios_android":99357,"ios_total":686088,"android_total":964595,"ios_android_total":1650683},{"data":"2020-06-06 00:00:00","ios":19575,"android":30659,"ios_android":50234,"ios_total":705663,"android_total":995254,"ios_android_total":1700917},{"data":"2020-06-07 00:00:00","ios":35598,"android":64361,"ios_android":99959,"ios_total":741261,"android_total":1059615,"ios_android_total":1800876},{"data":"2020-06-08 00:00:00","ios":54845,"android":173038,"ios_android":227883,"ios_total":796106,"android_total":1232653,"ios_android_total":2028759},{"data":"2020-06-09 00:00:00","ios":19422,"android":58087,"ios_android":77509,"ios_total":815528,"android_total":1290740,"ios_android_total":2106268},{"data":"2020-06-10 00:00:00","ios":9878,"android":39839,"ios_android":49717,"ios_total":825406,"android_total":1330579,"ios_android_total":2155985},{"data":"2020-06-11 00:00:00","ios":10758,"android":59138,"ios_android":69896,"ios_total":836164,"android_total":1389717,"ios_android_total":2225881},{"data":"2020-06-12 00:00:00","ios":15872,"android":62833,"ios_android":78705,"ios_total":852036,"android_total":1452550,"ios_android_total":2304586},{"data":"2020-06-13 00:00:00","ios":30599,"android":78088,"ios_android":108687,"ios_total":882635,"android_total":1530638,"ios_android_total":2413273},{"data":"2020-06-14 00:00:00","ios":25407,"android":105621,"ios_android":131028,"ios_total":908042,"android_total":1636259,"ios_android_total":2544301},{"data":"2020-06-15 00:00:00","ios":78873,"android":230138,"ios_android":309011,"ios_total":986915,"android_total":1866397,"ios_android_total":2853312},{"data":"2020-06-16 00:00:00","ios":38139,"android":119390,"ios_android":157529,"ios_total":1025054,"android_total":1985787,"ios_android_total":3010841},{"data":"2020-06-17 00:00:00","ios":24635,"android":203793,"ios_android":228428,"ios_total":1049689,"android_total":2189580,"ios_android_total":3239269},{"data":"2020-06-18 00:00:00","ios":19486,"android":78676,"ios_android":98162,"ios_total":1069175,"android_total":2268256,"ios_android_total":3337431},{"data":"2020-06-19 00:00:00","ios":15299,"android":48872,"ios_android":64171,"ios_total":1084474,"android_total":2317128,"ios_android_total":3401602},{"data":"2020-06-20 00:00:00","ios":15813,"android":52264,"ios_android":68077,"ios_total":1100287,"android_total":2369392,"ios_android_total":3469679},{"data":"2020-06-21 00:00:00","ios":16633,"android":55305,"ios_android":71938,"ios_total":1116920,"android_total":2424697,"ios_android_total":3541617},{"data":"2020-06-22 00:00:00","ios":10452,"android":29403,"ios_android":39855,"ios_total":1127372,"android_total":2454100,"ios_android_total":3581472},{"data":"2020-06-23 00:00:00","ios":10011,"android":28004,"ios_android":38015,"ios_total":1137383,"android_total":2482104,"ios_android_total":3619487},{"data":"2020-06-24 00:00:00","ios":7390,"android":25988,"ios_android":33378,"ios_total":1144773,"android_total":2508092,"ios_android_total":3652865},{"data":"2020-06-25 00:00:00","ios":8341,"android":25355,"ios_android":33696,"ios_total":1153114,"android_total":2533447,"ios_android_total":3686561},{"data":"2020-06-26 00:00:00","ios":9082,"android":27526,"ios_android":36608,"ios_total":1162196,"android_total":2560973,"ios_android_total":3723169},{"data":"2020-06-27 00:00:00","ios":8118,"android":28857,"ios_android":36975,"ios_total":1170314,"android_total":2589830,"ios_android_total":3760144},{"data":"2020-06-28 00:00:00","ios":10172,"android":33599,"ios_android":43771,"ios_total":1180486,"android_total":2623429,"ios_android_total":3803915},{"data":"2020-06-29 00:00:00","ios":5708,"android":17407,"ios_android":23115,"ios_total":1186194,"android_total":2640836,"ios_android_total":3827030},{"data":"2020-06-30 00:00:00","ios":4408,"android":14468,"ios_android":18876,"ios_total":1190602,"android_total":2655304,"ios_android_total":3845906},{"data":"2020-07-01 00:00:00","ios":4389,"android":55973,"ios_android":60362,"ios_total":1194991,"android_total":2711277,"ios_android_total":3906268},{"data":"2020-07-02 00:00:00","ios":4152,"android":19560,"ios_android":23712,"ios_total":1199143,"android_total":2730837,"ios_android_total":3929980},{"data":"2020-07-03 00:00:00","ios":5908,"android":18384,"ios_android":24292,"ios_total":1205051,"android_total":2749221,"ios_android_total":3954272},{"data":"2020-07-04 00:00:00","ios":4870,"android":15223,"ios_android":20093,"ios_total":1209921,"android_total":2764444,"ios_android_total":3974365},{"data":"2020-07-05 00:00:00","ios":4613,"android":14195,"ios_android":18808,"ios_total":1214534,"android_total":2778639,"ios_android_total":3993173},{"data":"2020-07-06 00:00:00","ios":5515,"android":15888,"ios_android":21403,"ios_total":1220049,"android_total":2794527,"ios_android_total":4014576},{"data":"2020-07-07 00:00:00","ios":4001,"android":11792,"ios_android":15793,"ios_total":1224050,"android_total":2806319,"ios_android_total":4030369},{"data":"2020-07-08 00:00:00","ios":3377,"android":9301,"ios_android":12678,"ios_total":1227427,"android_total":2815620,"ios_android_total":4043047},{"data":"2020-07-09 00:00:00","ios":3361,"android":10414,"ios_android":13775,"ios_total":1230788,"android_total":2826034,"ios_android_total":4056822},{"data":"2020-07-10 00:00:00","ios":3590,"android":11032,"ios_android":14622,"ios_total":1234378,"android_total":2837066,"ios_android_total":4071444},{"data":"2020-07-11 00:00:00","ios":2924,"android":9532,"ios_android":12456,"ios_total":1237302,"android_total":2846598,"ios_android_total":4083900},{"data":"2020-07-12 00:00:00","ios":2625,"android":8873,"ios_android":11498,"ios_total":1239927,"android_total":2855471,"ios_android_total":4095398},{"data":"2020-07-13 00:00:00","ios":2251,"android":7538,"ios_android":9789,"ios_total":1242178,"android_total":2863009,"ios_android_total":4105187},{"data":"2020-07-14 00:00:00","ios":2307,"android":12728,"ios_android":15035,"ios_total":1244485,"android_total":2875737,"ios_android_total":4120222},{"data":"2020-07-15 00:00:00","ios":2334,"android":24530,"ios_android":26864,"ios_total":1246819,"android_total":2900267,"ios_android_total":4147086},{"data":"2020-07-16 00:00:00","ios":2618,"android":28696,"ios_android":31314,"ios_total":1249437,"android_total":2928963,"ios_android_total":4178400},{"data":"2020-07-17 00:00:00","ios":2932,"android":32637,"ios_android":35569,"ios_total":1252369,"android_total":2961600,"ios_android_total":4213969},{"data":"2020-07-18 00:00:00","ios":2697,"android":26555,"ios_android":29252,"ios_total":1255066,"android_total":2988155,"ios_android_total":4243221},{"data":"2020-07-19 00:00:00","ios":2798,"android":27131,"ios_android":29929,"ios_total":1257864,"android_total":3015286,"ios_android_total":4273150},{"data":"2020-07-20 00:00:00","ios":2420,"android":24253,"ios_android":26673,"ios_total":1260284,"android_total":3039539,"ios_android_total":4299823},{"data":"2020-07-21 00:00:00","ios":2457,"android":23916,"ios_android":26373,"ios_total":1262741,"android_total":3063455,"ios_android_total":4326196},{"data":"2020-07-22 00:00:00","ios":2532,"android":24322,"ios_android":26854,"ios_total":1265273,"android_total":3087777,"ios_android_total":4353050},{"data":"2020-07-23 00:00:00","ios":4666,"android":30858,"ios_android":35524,"ios_total":1269939,"android_total":3118635,"ios_android_total":4388574},{"data":"2020-07-24 00:00:00","ios":4613,"android":26399,"ios_android":31012,"ios_total":1274552,"android_total":3145034,"ios_android_total":4419586},{"data":"2020-07-25 00:00:00","ios":2910,"android":10683,"ios_android":13593,"ios_total":1277462,"android_total":3155717,"ios_android_total":4433179},{"data":"2020-07-26 00:00:00","ios":3007,"android":8876,"ios_android":11883,"ios_total":1280469,"android_total":3164593,"ios_android_total":4445062},{"data":"2020-07-27 00:00:00","ios":2537,"android":7459,"ios_android":9996,"ios_total":1283006,"android_total":3172052,"ios_android_total":4455058},{"data":"2020-07-28 00:00:00","ios":2357,"android":8991,"ios_android":11348,"ios_total":1285363,"android_total":3181043,"ios_android_total":4466406},{"data":"2020-07-29 00:00:00","ios":3387,"android":17629,"ios_android":21016,"ios_total":1288750,"android_total":3198672,"ios_android_total":4487422},{"data":"2020-07-30 00:00:00","ios":2779,"android":16661,"ios_android":19440,"ios_total":1291529,"android_total":3215333,"ios_android_total":4506862},{"data":"2020-07-31 00:00:00","ios":4883,"android":21306,"ios_android":26189,"ios_total":1296412,"android_total":3236639,"ios_android_total":4533051},{"data":"2020-08-01 00:00:00","ios":4220,"android":18586,"ios_android":22806,"ios_total":1300632,"android_total":3255225,"ios_android_total":4555857},{"data":"2020-08-02 00:00:00","ios":3298,"android":16807,"ios_android":20105,"ios_total":1303930,"android_total":3272032,"ios_android_total":4575962},{"data":"2020-08-03 00:00:00","ios":3083,"android":14125,"ios_android":17208,"ios_total":1307013,"android_total":3286157,"ios_android_total":4593170},{"data":"2020-08-04 00:00:00","ios":3368,"android":8795,"ios_android":12163,"ios_total":1310381,"android_total":3294952,"ios_android_total":4605333},{"data":"2020-08-05 00:00:00","ios":4042,"android":9999,"ios_android":14041,"ios_total":1314423,"android_total":3304951,"ios_android_total":4619374},{"data":"2020-08-06 00:00:00","ios":4641,"android":12265,"ios_android":16906,"ios_total":1319064,"android_total":3317216,"ios_android_total":4636280},{"data":"2020-08-07 00:00:00","ios":4027,"android":10546,"ios_android":14573,"ios_total":1323091,"android_total":3327762,"ios_android_total":4650853},{"data":"2020-08-08 00:00:00","ios":3067,"android":7925,"ios_android":10992,"ios_total":1326158,"android_total":3335687,"ios_android_total":4661845},{"data":"2020-08-09 00:00:00","ios":3271,"android":8706,"ios_android":11977,"ios_total":1329429,"android_total":3344393,"ios_android_total":4673822},{"data":"2020-08-10 00:00:00","ios":3857,"android":9050,"ios_android":12907,"ios_total":1333286,"android_total":3353443,"ios_android_total":4686729},{"data":"2020-08-11 00:00:00","ios":4231,"android":11378,"ios_android":15609,"ios_total":1337517,"android_total":3364821,"ios_android_total":4702338},{"data":"2020-08-12 00:00:00","ios":4588,"android":11602,"ios_android":16190,"ios_total":1342105,"android_total":3376423,"ios_android_total":4718528},{"data":"2020-08-13 00:00:00","ios":4693,"android":11409,"ios_android":16102,"ios_total":1346798,"android_total":3387832,"ios_android_total":4734630},{"data":"2020-08-14 00:00:00","ios":5116,"android":12302,"ios_android":17418,"ios_total":1351914,"android_total":3400134,"ios_android_total":4752048},{"data":"2020-08-15 00:00:00","ios":4071,"android":10498,"ios_android":14569,"ios_total":1355985,"android_total":3410632,"ios_android_total":4766617},{"data":"2020-08-16 00:00:00","ios":4770,"android":14128,"ios_android":18898,"ios_total":1360755,"android_total":3424760,"ios_android_total":4785515},{"data":"2020-08-17 00:00:00","ios":12046,"android":24496,"ios_android":36542,"ios_total":1372801,"android_total":3449256,"ios_android_total":4822057},{"data":"2020-08-18 00:00:00","ios":7865,"android":17977,"ios_android":25842,"ios_total":1380666,"android_total":3467233,"ios_android_total":4847899},{"data":"2020-08-19 00:00:00","ios":7691,"android":17851,"ios_android":25542,"ios_total":1388357,"android_total":3485084,"ios_android_total":4873441},{"data":"2020-08-20 00:00:00","ios":9423,"android":22690,"ios_android":32113,"ios_total":1397780,"android_total":3507774,"ios_android_total":4905554},{"data":"2020-08-21 00:00:00","ios":9053,"android":22737,"ios_android":31790,"ios_total":1406833,"android_total":3530511,"ios_android_total":4937344},{"data":"2020-08-22 00:00:00","ios":8933,"android":22908,"ios_android":31841,"ios_total":1415766,"android_total":3553419,"ios_android_total":4969185},{"data":"2020-08-23 00:00:00","ios":10443,"android":26020,"ios_android":36463,"ios_total":1426209,"android_total":3579439,"ios_android_total":5005648},{"data":"2020-08-24 00:00:00","ios":11862,"android":25502,"ios_android":37364,"ios_total":1438071,"android_total":3604941,"ios_android_total":5043012},{"data":"2020-08-25 00:00:00","ios":13600,"android":33188,"ios_android":46788,"ios_total":1451671,"android_total":3638129,"ios_android_total":5089800},{"data":"2020-08-26 00:00:00","ios":15476,"android":34618,"ios_android":50094,"ios_total":1467147,"android_total":3672747,"ios_android_total":5139894},{"data":"2020-08-27 00:00:00","ios":13887,"android":26974,"ios_android":40861,"ios_total":1481034,"android_total":3699721,"ios_android_total":5180755},{"data":"2020-08-28 00:00:00","ios":10417,"android":27382,"ios_android":37799,"ios_total":1491451,"android_total":3727103,"ios_android_total":5218554},{"data":"2020-08-29 00:00:00","ios":7639,"android":20058,"ios_android":27697,"ios_total":1499090,"android_total":3747161,"ios_android_total":5246251},{"data":"2020-08-30 00:00:00","ios":7025,"android":20389,"ios_android":27414,"ios_total":1506115,"android_total":3767550,"ios_android_total":5273665},{"data":"2020-08-31 00:00:00","ios":12300,"android":30805,"ios_android":43105,"ios_total":1518415,"android_total":3798355,"ios_android_total":5316770},{"data":"2020-09-01 00:00:00","ios":8219,"android":21543,"ios_android":29762,"ios_total":1526634,"android_total":3819898,"ios_android_total":5346532},{"data":"2020-09-02 00:00:00","ios":7661,"android":19396,"ios_android":27057,"ios_total":1534295,"android_total":3839294,"ios_android_total":5373589},{"data":"2020-09-03 00:00:00","ios":7261,"android":18082,"ios_android":25343,"ios_total":1541556,"android_total":3857376,"ios_android_total":5398932},{"data":"2020-09-04 00:00:00","ios":8033,"android":18831,"ios_android":26864,"ios_total":1549589,"android_total":3876207,"ios_android_total":5425796},{"data":"2020-09-05 00:00:00","ios":7144,"android":19251,"ios_android":26395,"ios_total":1556733,"android_total":3895458,"ios_android_total":5452191},{"data":"2020-09-06 00:00:00","ios":7254,"android":18322,"ios_android":25576,"ios_total":1563987,"android_total":3913780,"ios_android_total":5477767},{"data":"2020-09-07 00:00:00","ios":6788,"android":17675,"ios_android":24463,"ios_total":1570775,"android_total":3931455,"ios_android_total":5502230},{"data":"2020-09-08 00:00:00","ios":8665,"android":17980,"ios_android":26645,"ios_total":1579440,"android_total":3949435,"ios_android_total":5528875},{"data":"2020-09-09 00:00:00","ios":8581,"android":17750,"ios_android":26331,"ios_total":1588021,"android_total":3967185,"ios_android_total":5555206},{"data":"2020-09-10 00:00:00","ios":7869,"android":32793,"ios_android":40662,"ios_total":1595890,"android_total":3999978,"ios_android_total":5595868},{"data":"2020-09-11 00:00:00","ios":7923,"android":91240,"ios_android":99163,"ios_total":1603813,"android_total":4091218,"ios_android_total":5695031},{"data":"2020-09-12 00:00:00","ios":7878,"android":76506,"ios_android":84384,"ios_total":1611691,"android_total":4167724,"ios_android_total":5779415},{"data":"2020-09-13 00:00:00","ios":10830,"android":72154,"ios_android":82984,"ios_total":1622521,"android_total":4239878,"ios_android_total":5862399},{"data":"2020-09-14 00:00:00","ios":12032,"android":62950,"ios_android":74982,"ios_total":1634553,"android_total":4302828,"ios_android_total":5937381},{"data":"2020-09-15 00:00:00","ios":9315,"android":49337,"ios_android":58652,"ios_total":1643868,"android_total":4352165,"ios_android_total":5996033},{"data":"2020-09-16 00:00:00","ios":9764,"android":50720,"ios_android":60484,"ios_total":1653632,"android_total":4402885,"ios_android_total":6056517},{"data":"2020-09-17 00:00:00","ios":9391,"android":41352,"ios_android":50743,"ios_total":1663023,"android_total":4444237,"ios_android_total":6107260},{"data":"2020-09-18 00:00:00","ios":7570,"android":35757,"ios_android":43327,"ios_total":1670593,"android_total":4479994,"ios_android_total":6150587},{"data":"2020-09-19 00:00:00","ios":7379,"android":33948,"ios_android":41327,"ios_total":1677972,"android_total":4513942,"ios_android_total":6191914},{"data":"2020-09-20 00:00:00","ios":6703,"android":32843,"ios_android":39546,"ios_total":1684675,"android_total":4546785,"ios_android_total":6231460},{"data":"2020-09-21 00:00:00","ios":6213,"android":29892,"ios_android":36105,"ios_total":1690888,"android_total":4576677,"ios_android_total":6267565},{"data":"2020-09-22 00:00:00","ios":5282,"android":28547,"ios_android":33829,"ios_total":1696170,"android_total":4605224,"ios_android_total":6301394},{"data":"2020-09-23 00:00:00","ios":5530,"android":28112,"ios_android":33642,"ios_total":1701700,"android_total":4633336,"ios_android_total":6335036},{"data":"2020-09-24 00:00:00","ios":6447,"android":28655,"ios_android":35102,"ios_total":1708147,"android_total":4661991,"ios_android_total":6370138},{"data":"2020-09-25 00:00:00","ios":5734,"android":26404,"ios_android":32138,"ios_total":1713881,"android_total":4688395,"ios_android_total":6402276},{"data":"2020-09-26 00:00:00","ios":4364,"android":23379,"ios_android":27743,"ios_total":1718245,"android_total":4711774,"ios_android_total":6430019},{"data":"2020-09-27 00:00:00","ios":5253,"android":26338,"ios_android":31591,"ios_total":1723498,"android_total":4738112,"ios_android_total":6461610},{"data":"2020-09-28 00:00:00","ios":13066,"android":39354,"ios_android":52420,"ios_total":1736564,"android_total":4777466,"ios_android_total":6514030},{"data":"2020-09-29 00:00:00","ios":6526,"android":26727,"ios_android":33253,"ios_total":1743090,"android_total":4804193,"ios_android_total":6547283},{"data":"2020-09-30 00:00:00","ios":5691,"android":25860,"ios_android":31551,"ios_total":1748781,"android_total":4830053,"ios_android_total":6578834},{"data":"2020-10-01 00:00:00","ios":9060,"android":31610,"ios_android":40670,"ios_total":1757841,"android_total":4861663,"ios_android_total":6619504},{"data":"2020-10-02 00:00:00","ios":19161,"android":59679,"ios_android":78840,"ios_total":1777002,"android_total":4921342,"ios_android_total":6698344},{"data":"2020-10-03 00:00:00","ios":38080,"android":113667,"ios_android":151747,"ios_total":1815082,"android_total":5035009,"ios_android_total":6850091},{"data":"2020-10-04 00:00:00","ios":31829,"android":95945,"ios_android":127774,"ios_total":1846911,"android_total":5130954,"ios_android_total":6977865},{"data":"2020-10-05 00:00:00","ios":63012,"android":163907,"ios_android":226919,"ios_total":1909923,"android_total":5294861,"ios_android_total":7204784},{"data":"2020-10-06 00:00:00","ios":61914,"android":159441,"ios_android":221355,"ios_total":1971837,"android_total":5454302,"ios_android_total":7426139},{"data":"2020-10-07 00:00:00","ios":62103,"android":169592,"ios_android":231695,"ios_total":2033940,"android_total":5623894,"ios_android_total":7657834},{"data":"2020-10-08 00:00:00","ios":65677,"android":175696,"ios_android":241373,"ios_total":2099617,"android_total":5799590,"ios_android_total":7899207},{"data":"2020-10-09 00:00:00","ios":50476,"android":138829,"ios_android":189305,"ios_total":2150093,"android_total":5938419,"ios_android_total":8088512},{"data":"2020-10-10 00:00:00","ios":41867,"android":128903,"ios_android":170770,"ios_total":2191960,"android_total":6067322,"ios_android_total":8259282},{"data":"2020-10-11 00:00:00","ios":50409,"android":134156,"ios_android":184565,"ios_total":2242369,"android_total":6201478,"ios_android_total":8443847},{"data":"2020-10-12 00:00:00","ios":27737,"android":77133,"ios_android":104870,"ios_total":2270106,"android_total":6278611,"ios_android_total":8548717},{"data":"2020-10-13 00:00:00","ios":22253,"android":60156,"ios_android":82409,"ios_total":2292359,"android_total":6338767,"ios_android_total":8631126},{"data":"2020-10-14 00:00:00","ios":19188,"android":54486,"ios_android":73674,"ios_total":2311547,"android_total":6393253,"ios_android_total":8704800},{"data":"2020-10-15 00:00:00","ios":22016,"android":54787,"ios_android":76803,"ios_total":2333563,"android_total":6448040,"ios_android_total":8781603},{"data":"2020-10-16 00:00:00","ios":19898,"android":57237,"ios_android":77135,"ios_total":2353461,"android_total":6505277,"ios_android_total":8858738},{"data":"2020-10-17 00:00:00","ios":15353,"android":45553,"ios_android":60906,"ios_total":2368814,"android_total":6550830,"ios_android_total":8919644},{"data":"2020-10-18 00:00:00","ios":13604,"android":43167,"ios_android":56771,"ios_total":2382418,"android_total":6593997,"ios_android_total":8976415},{"data":"2020-10-19 00:00:00","ios":19955,"android":48812,"ios_android":68767,"ios_total":2402373,"android_total":6642809,"ios_android_total":9045182},{"data":"2020-10-20 00:00:00","ios":15823,"android":42539,"ios_android":58362,"ios_total":2418196,"android_total":6685348,"ios_android_total":9103544},{"data":"2020-10-21 00:00:00","ios":20633,"android":47265,"ios_android":67898,"ios_total":2438829,"android_total":6732613,"ios_android_total":9171442},{"data":"2020-10-22 00:00:00","ios":15091,"android":38939,"ios_android":54030,"ios_total":2453920,"android_total":6771552,"ios_android_total":9225472},{"data":"2020-10-23 00:00:00","ios":11946,"android":33510,"ios_android":45456,"ios_total":2465866,"android_total":6805062,"ios_android_total":9270928},{"data":"2020-10-24 00:00:00","ios":11538,"android":33128,"ios_android":44666,"ios_total":2477404,"android_total":6838190,"ios_android_total":9315594},{"data":"2020-10-25 00:00:00","ios":14545,"android":37100,"ios_android":51645,"ios_total":2491949,"android_total":6875290,"ios_android_total":9367239},{"data":"2020-10-26 00:00:00","ios":12601,"android":26950,"ios_android":39551,"ios_total":2504550,"android_total":6902240,"ios_android_total":9406790},{"data":"2020-10-27 00:00:00","ios":8697,"android":25446,"ios_android":34143,"ios_total":2513247,"android_total":6927686,"ios_android_total":9440933},{"data":"2020-10-28 00:00:00","ios":10373,"android":26940,"ios_android":37313,"ios_total":2523620,"android_total":6954626,"ios_android_total":9478246},{"data":"2020-10-29 00:00:00","ios":9005,"android":24382,"ios_android":33387,"ios_total":2532625,"android_total":6979008,"ios_android_total":9511633},{"data":"2020-10-30 00:00:00","ios":7827,"android":22237,"ios_android":30064,"ios_total":2540452,"android_total":7001245,"ios_android_total":9541697},{"data":"2020-10-31 00:00:00","ios":6277,"android":20398,"ios_android":26675,"ios_total":2546729,"android_total":7021643,"ios_android_total":9568372},{"data":"2020-11-01 00:00:00","ios":7187,"android":22565,"ios_android":29752,"ios_total":2553916,"android_total":7044208,"ios_android_total":9598124},{"data":"2020-11-02 00:00:00","ios":7835,"android":22268,"ios_android":30103,"ios_total":2561751,"android_total":7066476,"ios_android_total":9628227},{"data":"2020-11-03 00:00:00","ios":5820,"android":17939,"ios_android":23759,"ios_total":2567571,"android_total":7084415,"ios_android_total":9651986},{"data":"2020-11-04 00:00:00","ios":4923,"android":17535,"ios_android":22458,"ios_total":2572494,"android_total":7101950,"ios_android_total":9674444},{"data":"2020-11-05 00:00:00","ios":3819,"android":15746,"ios_android":19565,"ios_total":2576313,"android_total":7117696,"ios_android_total":9694009},{"data":"2020-11-06 00:00:00","ios":3414,"android":13853,"ios_android":17267,"ios_total":2579727,"android_total":7131549,"ios_android_total":9711276},{"data":"2020-11-07 00:00:00","ios":3097,"android":13794,"ios_android":16891,"ios_total":2582824,"android_total":7145343,"ios_android_total":9728167},{"data":"2020-11-08 00:00:00","ios":3110,"android":11443,"ios_android":14553,"ios_total":2585934,"android_total":7156786,"ios_android_total":9742720},{"data":"2020-11-09 00:00:00","ios":3331,"android":11032,"ios_android":14363,"ios_total":2589265,"android_total":7167818,"ios_android_total":9757083},{"data":"2020-11-10 00:00:00","ios":2580,"android":9709,"ios_android":12289,"ios_total":2591845,"android_total":7177527,"ios_android_total":9769372},{"data":"2020-11-11 00:00:00","ios":2219,"android":8989,"ios_android":11208,"ios_total":2594064,"android_total":7186516,"ios_android_total":9780580},{"data":"2020-11-12 00:00:00","ios":2037,"android":8906,"ios_android":10943,"ios_total":2596101,"android_total":7195422,"ios_android_total":9791523},{"data":"2020-11-13 00:00:00","ios":2048,"android":9087,"ios_android":11135,"ios_total":2598149,"android_total":7204509,"ios_android_total":9802658},{"data":"2020-11-14 00:00:00","ios":2416,"android":9448,"ios_android":11864,"ios_total":2600565,"android_total":7213957,"ios_android_total":9814522},{"data":"2020-11-15 00:00:00","ios":2267,"android":8555,"ios_android":10822,"ios_total":2602832,"android_total":7222512,"ios_android_total":9825344},{"data":"2020-11-16 00:00:00","ios":1876,"android":8130,"ios_android":10006,"ios_total":2604708,"android_total":7230642,"ios_android_total":9835350},{"data":"2020-11-17 00:00:00","ios":1575,"android":7404,"ios_android":8979,"ios_total":2606283,"android_total":7238046,"ios_android_total":9844329},{"data":"2020-11-18 00:00:00","ios":854,"android":6796,"ios_android":7650,"ios_total":2607137,"android_total":7244842,"ios_android_total":9851979}]